outscraper/__init__.py
outscraper/api_client.py
outscraper/utils.py
google_services_api-1.5.0.dist-info/LICENSE
google_services_api-1.5.0.dist-info/METADATA
google_services_api-1.5.0.dist-info/WHEEL
google_services_api-1.5.0.dist-info/top_level.txt
google_services_api-1.5.0.dist-info/RECORD
