Metadata-Version: 2.1
Name: google-services-api
Version: 1.5.0
Summary: Google Maps and Google Maps reviews scraper by Outscraper API
Home-page: https://github.com/outscraper/google-maps-scraper-pyhton
Author: Outscraper
Author-email: team@outscraper.com
License: MIT
Keywords: extractor google api maps search json scrape parser reviews google play
Classifier: Programming Language :: Python
Classifier: License :: OSI Approved :: MIT License
Classifier: Operating System :: OS Independent
Classifier: Intended Audience :: Developers
Classifier: Topic :: Utilities
License-File: LICENSE
Requires-Dist: requests
